CHANGES.rst
CONTRIBUTORS.rst
MANIFEST.in
README.rst
setup.cfg
setup.py
docs/LICENSE.GPL
docs/LICENSE.txt
src/collective/__init__.py
src/collective.behavior.localdiazo.egg-info/PKG-INFO
src/collective.behavior.localdiazo.egg-info/SOURCES.txt
src/collective.behavior.localdiazo.egg-info/dependency_links.txt
src/collective.behavior.localdiazo.egg-info/entry_points.txt
src/collective.behavior.localdiazo.egg-info/namespace_packages.txt
src/collective.behavior.localdiazo.egg-info/not-zip-safe
src/collective.behavior.localdiazo.egg-info/requires.txt
src/collective.behavior.localdiazo.egg-info/top_level.txt
src/collective/behavior/__init__.py
src/collective/behavior/localdiazo/__init__.py
src/collective/behavior/localdiazo/behavior.py
src/collective/behavior/localdiazo/behavior.rst
src/collective/behavior/localdiazo/browser.py
src/collective/behavior/localdiazo/browser.rst
src/collective/behavior/localdiazo/configure.zcml
src/collective/behavior/localdiazo/subscribers.py
src/collective/behavior/localdiazo/testing.py
src/collective/behavior/localdiazo/locales/collective.behavior.localdiazo.pot
src/collective/behavior/localdiazo/locales/manual.pot
src/collective/behavior/localdiazo/locales/plone.pot
src/collective/behavior/localdiazo/locales/es/LC_MESSAGES/collective.behavior.localdiazo.po
src/collective/behavior/localdiazo/locales/es/LC_MESSAGES/plone.po
src/collective/behavior/localdiazo/locales/pt_BR/LC_MESSAGES/collective.behavior.localdiazo.po
src/collective/behavior/localdiazo/locales/pt_BR/LC_MESSAGES/plone.po
src/collective/behavior/localdiazo/tests/__init__.py
src/collective/behavior/localdiazo/tests/test_setup.py